Metadata-Version: 1.1
Name: sample-s3
Version: 0.0.4
Summary: Create a sample data set from a large CSV file on Amazon S3.
Home-page: https://github.com/briandailey/sample-s3-csv
Author: Brian Dailey
Author-email: brian@realm3.com
License: MIT
Keywords: aws s3 data csv
Platform: UNKNOWN
Classifier: Development Status :: 3 - Alpha
Classifier: Intended Audience :: Developers
Classifier: Topic :: Software Development :: Build Tools
Classifier: License :: OSI Approved :: MIT License
Classifier: Programming Language :: Python :: 3.5
